slack_airflow_dag_alert/__init__.py
slack_airflow_dag_alert/slack_airflow_dag_alert.py
slack_airflow_dag_alert-1.0.0.dist-info/METADATA
slack_airflow_dag_alert-1.0.0.dist-info/WHEEL
slack_airflow_dag_alert-1.0.0.dist-info/top_level.txt
slack_airflow_dag_alert-1.0.0.dist-info/RECORD
